pookla/__init__.py
pookla-0.0.1.dist-info/METADATA
pookla-0.0.1.dist-info/WHEEL
pookla-0.0.1.dist-info/top_level.txt
pookla-0.0.1.dist-info/RECORD
