Metadata-Version: 2.1
Name: pookla
Version: 0.0.1
Summary: Pookla
Home-page: https://github.com/teamookla
Author: Jeremy Jacobs
Author-email: jeremy.jacobs@ookla.com
License: UNKNOWN
Platform: UNKNOWN
Requires-Python: >=3.8.3
